ipfs_model_manager_py/__init__.py
ipfs_model_manager_py/ipfs_model_manager.py
ipfs_model_manager_py/test_fio.py
ipfs_model_manager_py/aria2/aria2.py
ipfs_model_manager_py/aria2/aria2c
ipfs_model_manager_py/s3_kit/s3_kit.py
ipfs_model_manager_py/test/test_fio.py
ipfs_model_manager_py/test/test_hf_ipfs.py
ipfs_model_manager_py-0.0.23.dist-info/LICENSE
ipfs_model_manager_py-0.0.23.dist-info/METADATA
ipfs_model_manager_py-0.0.23.dist-info/WHEEL
ipfs_model_manager_py-0.0.23.dist-info/top_level.txt
ipfs_model_manager_py-0.0.23.dist-info/RECORD
